cyberfusion/SelfDiscover/__init__.py
cyberfusion/SelfDiscover/exceptions.py
cyberfusion/SelfDiscover/main.py
cyberfusion/SelfDiscover/settings.py
cyberfusion/SelfDiscover/utilities.py
python3_cyberfusion_self_discover-1.1.dist-info/METADATA
python3_cyberfusion_self_discover-1.1.dist-info/WHEEL
python3_cyberfusion_self_discover-1.1.dist-info/top_level.txt
python3_cyberfusion_self_discover-1.1.dist-info/RECORD
