Metadata-Version: 2.4
Name: python3-cyberfusion-self-discover
Version: 1.1
Summary: self-discover serves autodiscover (Outlook) and autoconfig (Thunderbird) XML files for mail auto-configuration.
Author-email: Cyberfusion <support@cyberfusion.io>
Project-URL: Source, https://github.com/CyberfusionIO/python3-cyberfusion-self-discover
Requires-Dist: fastapi==0.115.11
Requires-Dist: uvicorn==0.32.0
Requires-Dist: defusedxml==0.7.1
Requires-Dist: pydantic-settings==2.8.1
